{"Derrick Henry": 33.24, "Dalvin Cook": 32.3, "Joe Mixon": 30.0, "Marlon Mack": 29.9, "Chris Carson": 29.8, "Matt Ryan": 27.04, "Davante Adams": 24.9, "Kenny Golladay": 24.6, "Robert Foster": 23.8, "Doug Baldwin": 23.7, "Tevin Coleman": 23.5, "Jaylen Samuels": 22.2, "Kalen Ballage": 22.1, "Julio Jones": 20.2, "Falcons": 20.0, "Ezekiel Elliott": 19.8, "Josh Allen": 19.76, "Jamaal Williams": 19.7, "Gus Edwards": 19.4, "David Johnson": 19.1, "Mike Evans": 19.1, "Mitchell Trubisky": 19.0, "Russell Wilson": 18.98, "Lamar Jackson": 17.74, "Colts": 17.0, "Titans": 17.0, "Peyton Barber": 16.9, "Mike Davis": 16.4, "Kirk Cousins": 16.3, "Julian Edelman": 16.0, "Stefon Diggs": 15.8, "Tarik Cohen": 15.5, "Evan Engram": 15.5, "Larry Fitzgerald": 15.2, "Ben Roethlisberger": 15.1, "Josh Johnson": 14.94, "Antonio Brown": 14.9, "Chris Hogan": 14.8, "Nick Mullens": 14.8, "Jordy Nelson": 14.8, "Matt Breida": 14.6, "Jordan Howard": 14.5, "Aaron Rodgers": 14.46, "Tom Brady": 14.16, "Garrett Celek": 14.1, "Redskins": 14.0, "Tyler Boyd": 13.8, "Derek Carr": 13.62, "Trey Burton": 13.6, "T.Y. Hilton": 13.5, "Zach Zenner": 13.5, "Dante Pettis": 13.3, "Dede Westbrook": 13.1, "Vikings": 13.0, "Latavius Murray": 12.8, "Aldrick Robinson": 12.4, "Matthew Stafford": 12.32, "Justin Hardy": 11.9, "Isaiah McKenzie": 11.7, "Jalen Richard": 11.6, "Jeff Driskel": 11.4, "Jeremy Sprinkle": 10.9, "Willie Snead IV": 10.8, "Trent Sherfield": 10.5, "Nyheim Hines": 10.4, "Bengals": 10.0, "Jaguars": 10.0, "Andrew Luck": 9.68, "Saquon Barkley": 9.6, "James Washington": 9.5, "Leonard Fournette": 9.4, "Vance McDonald": 9.3, "Calvin Ridley": 9.2, "Adrian Peterson": 9.1, "49ers": 9.0, "Andy Jones": 8.9, "James White": 8.7, "Jamison Crowder": 8.6, "Blake Jarwin": 8.5, "Mike Glennon": 8.44, "Allen Robinson II": 8.4, "Amari Cooper": 8.3, "Cole Beasley": 8.2, "George Kittle": 8.1, "Bears": 8.0, "JuJu Smith-Schuster": 8.0, "Theo Riddick": 7.6, "Tyler Lockett": 7.6, "Darren Waller": 7.5, "Dion Lewis": 7.4, "Tyler Conklin": 7.3, "Rex Burkhead": 7.3, "Dak Prescott": 7.24, "Eli Manning": 7.16, "Mohamed Sanu": 7.1, "Lee Smith": 7.1, "Cody Kessler": 7.08, "Chris Moore": 7.0, "Ravens": 7.0, "Steelers": 7.0, "Buccaneers": 7.0, "Patriots": 7.0, "Levine Toilolo": 6.8, "Lance Kendricks": 6.7, "Chase Edmonds": 6.4, "Kenyan Drake": 6.4, "Corey Davis": 6.3, "Adam Humphries": 6.3, "Bennie Fowler": 6.3, "Keith Ford": 6.3, "Taylor Gabriel": 6.3, "Jimmy Graham": 6.2, "Dolphins": 6.0, "Richie James Jr.": 6.0, "Eli Rogers": 6.0, "Randall Cobb": 6.0, "Danny Amendola": 6.0, "Kenneth Dixon": 6.0, "Ito Smith": 5.9, "Adam Shaheen": 5.9, "Sony Michel": 5.9, "Seth Roberts": 5.7, "Sterling Shepard": 5.7, "T.J. Logan": 5.5, "Kyle Rudolph": 5.3, "Dalton Schultz": 5.3, "Alex Erickson": 5.3, "Russell Gage": 5.3, "Jameis Winston": 5.28, "Ricky Seals-Jones": 5.2, "Giovani Bernard": 5.2, "Mark Andrews": 5.1, "Seahawks": 5.0, "Cordarrelle Patterson": 5.0, "Hayden Hurst": 5.0, "Russell Shepard": 4.8, "Luke Stocker": 4.7, "Marcus Mariota": 4.62, "Brandon Powell": 4.5, "Ryan Tannehill": 4.42, "Mike Gesicki": 4.3, "Jared Cook": 4.3, "Rob Gronkowski": 4.1, "Bills": 4.0, "Marcell Ateman": 4.0, "Adam Thielen": 3.9, "Doug Martin": 3.9, "James Develin": 3.8, "C.J. Uzomah": 3.7, "Taywan Taylor": 3.7, "Ryan Grant": 3.6, "Jeff Wilson Jr.": 3.6, "Michael Floyd": 3.6, "Kendrick Bourne": 3.6, "Vernon Davis": 3.6, "Jason Croom": 3.5, "Marcus Murphy": 3.5, "Ed Dickson": 3.4, "Jawill Davis": 3.3, "Ryan Switzer": 3.2, "Josh Rosen": 3.08, "Packers": 3.0, "Josh Gordon": 2.9, "Josh Bellamy": 2.8, "Kenny Stills": 2.7, "Byron Marshall": 2.7, "Jermaine Gresham": 2.6, "Noah Brown": 2.4, "Maurice Harris": 2.3, "Chris Thompson": 2.3, "Marquez Valdes-Scantling": 2.2, "Zach Pascal": 2.2, "Brice Butler": 2.2, "Zay Jones": 2.1, "T.J. Yeldon": 2.1, "Lions": 2.0, "Taquan Mizzell": 2.0, "Chester Rogers": 2.0, "Cody Core": 2.0, "Giants": 2.0, "Cowboys": 2.0, "Marvin Hall": 2.0, "Raiders": 2.0, "Allen Hurns": 1.9, "John Ross": 1.9, "Jesse James": 1.9, "Cameron Brate": 1.9, "John Brown": 1.9, "David Moore": 1.9, "Trent Taylor": 1.8, "Corey Coleman": 1.8, "Eric Ebron": 1.8, "Marquise Goodwin": 1.7, "James O'Shaughnessy": 1.7, "Equanimeous St. Brown": 1.7, "Jordan Wilkins": 1.6, "Tajae Sharpe": 1.6, "Blake Bell": 1.6, "Maxx Williams": 1.6, "Stevan Ridley": 1.6, "TJ Jones": 1.5, "Jake Kumerow": 1.5, "Frank Gore": 1.4, "Rod Smith": 1.4, "Kyle Juszczyk": 1.3, "MyCole Pruitt": 1.2, "Brandon Bolden": 1.2, "Jacquizz Rodgers": 1.1, "Cardinals": 1.0, "LeGarrette Blount": 0.9, "Ronald Jones II": 0.9, "Patrick DiMarco": 0.9, "Aaron Jones": 0.8, "Ray-Ray McCloud III": 0.7, "Brian Hill": 0.7, "J.D. McKissic": 0.2, "Elijhaa Penny": 0.2, "DeAndre Washington": 0.1, "Scott Simonson": 0.0, "Josh Doctson": 0.0, "Wayne Gallman": 0.0, "David Williams": 0.0, "Daniel Brown": 0.0, "Leonte Carroo": 0.0, "Ben Koyack": 0.0, "Brett Hundley": 0.0, "Senorise Perry": 0.0, "Trey Edmunds": 0.0, "Michael Crabtree": 0.0, "Clark Harris": 0.0, "Cameron Batson": 0.0, "Brock Osweiler": 0.0, "Brian Hoyer": 0.0, "Javorius Allen": 0.0, "C.J. Ham": 0.0, "Jerome Cunningham": 0.0, "Matt Lengel": 0.0, "Ryan Hewitt": 0.0, "Jaron Brown": 0.0, "Derrick Coleman": 0.0, "Bobo Wilson": 0.0, "Austin Hooper": 0.0, "Rico Gathers": 0.0, "Xavier Grimble": 0.0, "Matt Cassel": 0.0, "Ben Braunecker": 0.0, "Antony Auclair": 0.0, "Jalen Tolliver": 0.0, "Auden Tate": 0.0, "Keelan Cole": 0.0, "Malik Turner": 0.0, "Joe Flacco": 0.0, "Tre Madden": 0.0, "Kevin McDermott": 0.0, "Blake Bortles": 0.0, "Eric Saubert": 0.0, "Derek Carrier": 0.0, "David Morgan": 0.0, "Donte Moncrief": 0.0, "Nick Vannett": 0.0, "DeShone Kizer": 0.0, "Cooper Rush": 0.0, "Jamize Olawale": 0.0, "Roosevelt Nix": 0.0, "Robert Tonyan": 0.0, "Anthony Firkser": 0.0, "Durham Smythe": 0.0, "Matt Flanagan": 0.0, "Lance Lenoir": 0.0, "Ryan Fitzpatrick": 0.0, "Keith Smith": 0.0, "Marcedes Lewis": 0.0, "Luke Willson": 0.0, "Dwayne Harris": 0.0, "Darrius Heyward-Bey": 0.0, "Matt Schaub": 0.0, "Mark Sanchez": 0.0, "Danny Vitale": 0.0, "Alan Cross": 0.0, "Nick O'Leary": 0.0, "Rashad Greene Sr.": 0.0, "Tom Savage": 0.0, "Jacoby Brissett": 0.0, "Chris Godwin": 0.0, "Laquon Treadwell": 0.0, "Jehu Chesson": 0.0, "Mo Alie-Cox": 0.0, "Alex Tanney": 0.0, "Anthony Miller": 0.0, "Charles Clay": 0.0, "John Phillips": 0.0, "Beau Brinkley": 0.0, "Matthew Slater": 0.0, "Mark Walton": 0.0, "Tommy Bohanon": 0.0, "Matt Dayes": 0.0, "Nick Boyle": 0.0, "J.J. Nelson": 0.0, "Darius Jennings": 0.0, "DeVante Parker": 0.0, "Tyler Ott": 0.0, "Dwayne Allen": 0.0, "Chase Daniel": 0.0, "AJ McCarron": 0.0, "Da'Mari Scott": 0.0, "Justin Watson": 0.0, "Ross Dwelley": 0.0, "Phillip Dorsett": 0.0, "Matt Barkley": 0.0, "C.J. Beathard": 0.0, "Ameer Abdullah": 0.0, "J'Mon Moore": 0.0, "Deonte Thompson": 0.0, "Logan Paulsen": 0.0, "Rhett Ellison": 0.0, "Brandon Zylstra": 0.0, "Dontrelle Inman": 0.0, "Michael Gallup": 0.0, "Trevor Siemian": 0.0, "Joshua Dobbs": 0.0, "Patrick Scales": 0.0, "Blaine Gabbert": -0.1, "Benny Cunningham": -0.1}