{"Ben Roethlisberger": 41.98, "Patrick Mahomes": 41.84, "Stefon Diggs": 38.9, "Kirk Cousins": 37.5, "Blake Bortles": 36.54, "Adam Thielen": 34.1, "JuJu Smith-Schuster": 34.1, "Ryan Fitzpatrick": 33.98, "Travis Kelce": 32.9, "Todd Gurley II": 32.3, "Michael Thomas": 31.9, "Matt Ryan": 31.68, "Cam Newton": 31.6, "Christian McCaffrey": 30.9, "Melvin Gordon": 30.6, "Matthew Stafford": 28.68, "Will Fuller V": 28.3, "Matt Breida": 27.9, "Jesse James": 27.8, "Keelan Cole": 27.6, "Deshaun Watson": 26.8, "DeAndre Hopkins": 26.0, "Brandin Cooks": 25.9, "DeSean Jackson": 25.9, "Amari Cooper": 24.6, "Mike Evans": 23.3, "Nelson Agholor": 23.0, "Philip Rivers": 22.74, "Jared Goff": 22.36, "Chris Thompson": 22.3, "Sammy Watkins": 22.1, "Golden Tate": 21.8, "T.Y. Hilton": 21.3, "Kenny Golladay": 20.9, "Zach Ertz": 20.4, "Davante Adams": 20.4, "Tyreek Hill": 20.0, "Nick Foles": 19.66, "James Conner": 19.5, "Corey Clement": 19.5, "Tevin Coleman": 19.5, "Chris Hogan": 19.2, "Bilal Powell": 19.0, "O.J. Howard": 18.6, "Sam Darnold": 18.46, "Ryan Tannehill": 18.12, "Alvin Kamara": 17.9, "Antonio Callaway": 17.8, "Drew Brees": 17.62, "Dede Westbrook": 17.6, "Tom Brady": 17.36, "Jarius Wright": 17.2, "Kenyan Drake": 17.0, "Austin Hooper": 16.9, "Calvin Ridley": 16.7, "Jimmy Garoppolo": 16.64, "Chris Godwin": 16.6, "Quincy Enunwa": 16.2, "Aaron Rodgers": 16.04, "Antonio Brown": 15.7, "Derek Carr": 15.52, "Jimmy Graham": 15.5, "Case Keenum": 15.48, "Tyrod Taylor": 15.44, "Marvin Jones Jr.": 15.4, "James White": 15.4, "Phillip Lindsay": 15.1, "Kareem Hunt": 15.0, "Josh Allen": 15.0, "Marshawn Lynch": 14.8, "Devin Funchess": 14.7, "Kyle Rudolph": 14.2, "Robert Woods": 14.1, "Theo Riddick": 13.7, "Emmanuel Sanders": 13.6, "Albert Wilson": 13.5, "Donte Moncrief": 13.4, "Andrew Luck": 13.36, "Seth Roberts": 13.3, "Alex Smith": 13.08, "Dolphins": 13.0, "Rams": 13.0, "Corey Grant": 12.9, "Austin Ekeler": 12.8, "D.J. Moore": 12.8, "Keenan Allen": 12.7, "Geronimo Allison": 12.4, "Terrelle Pryor Sr.": 12.4, "Torrey Smith": 12.3, "Cooper Kupp": 12.3, "Taywan Taylor": 12.2, "Carlos Hyde": 12.0, "Dalvin Cook": 12.0, "Jarvis Landry": 11.9, "Eric Ebron": 11.6, "Kerryon Johnson": 11.6, "Julio Jones": 11.4, "Austin Seferian-Jenkins": 11.3, "LeSean McCoy": 10.8, "Chris Ivory": 10.7, "Mike Williams": 10.7, "Corey Davis": 10.5, "Jordan Reed": 10.5, "Paul Richardson Jr.": 10.3, "Laquon Treadwell": 10.3, "Garrett Celek": 10.2, "Jamaal Williams": 10.1, "Chargers": 10.0, "Alfred Morris": 10.0, "Kelvin Benjamin": 9.9, "Rashard Higgins": 9.7, "Joshua Perkins": 9.7, "Jay Ajayi": 9.7, "Pierre Garcon": 9.7, "Phillip Dorsett": 9.4, "T.J. Yeldon": 9.1, "Colts": 9.0, "Lamar Miller": 9.0, "Jets": 9.0, "Kamar Aiken": 8.9, "Jared Cook": 8.9, "A.J. Derby": 8.9, "Blaine Gabbert": 8.88, "Jake Butt": 8.8, "Royce Freeman": 8.8, "Chris Conley": 8.7, "Virgil Green": 8.5, "Ted Ginn Jr.": 8.5, "Michael Roberts": 8.5, "Jordan Wilkins": 8.4, "James Washington": 8.4, "Zay Jones": 8.3, "Adrian Peterson": 8.0, "Tyrell Williams": 7.8, "Josh Doctson": 7.7, "Bruce Ellington": 7.5, "Nyheim Hines": 7.5, "Kendrick Bourne": 7.4, "Demarcus Robinson": 7.3, "Tyler Higbee": 7.3, "Danny Amendola": 7.2, "Randall Cobb": 7.0, "Martavis Bryant": 7.0, "Buccaneers": 7.0, "Browns": 7.0, "Chase Edmonds": 7.0, "Titans": 7.0, "Demaryius Thomas": 6.8, "Christian Kirk": 6.7, "Jacquizz Rodgers": 6.6, "Malcolm Brown": 6.6, "Jacob Hollister": 6.5, "Ito Smith": 6.4, "David Johnson": 6.1, "Saints": 6.0, "Eagles": 6.0, "David Njoku": 6.0, "Derrick Henry": 5.92, "Isaiah Crowell": 5.9, "Larry Fitzgerald": 5.8, "Jamison Crowder": 5.7, "Ricky Seals-Jones": 5.7, "Vance McDonald": 5.6, "Frank Gore": 5.4, "Dion Lewis": 5.3, "Cordarrelle Patterson": 5.3, "Jakeem Grant": 5.2, "Sony Michel": 5.1, "Packers": 5.0, "Ryan Grant": 5.0, "Redskins": 5.0, "Christopher Herndon IV": 5.0, "Lions": 5.0, "Jaguars": 5.0, "Robert Foster": 5.0, "Ty Montgomery": 5.0, "Jordy Nelson": 5.0, "Charles Clay": 4.9, "Benjamin Watson": 4.9, "Chester Rogers": 4.7, "Robby Anderson": 4.7, "Marlon Mack": 4.6, "Dante Pettis": 4.5, "LeGarrette Blount": 4.5, "Kyle Juszczyk": 4.3, "George Kittle": 4.2, "Jordan Akins": 4.1, "49ers": 4.0, "Marvin Hall": 4.0, "Broncos": 4.0, "Jack Doyle": 4.0, "Falcons": 4.0, "Raiders": 4.0, "Peyton Barber": 3.9, "David Morgan": 3.9, "Kenny Stills": 3.7, "Tim Patrick": 3.6, "Alfred Blue": 3.6, "Rob Gronkowski": 3.5, "Darren Fells": 3.5, "Mohamed Sanu": 3.5, "Luke Stocker": 3.5, "Doug Martin": 3.4, "Eric Tomlinson": 3.4, "Patrick DiMarco": 3.4, "Niles Paul": 3.2, "Keith Smith": 3.2, "C.J. Anderson": 3.1, "Ian Thomas": 3.0, "Duke Johnson Jr.": 3.0, "Jeff Heuerman": 3.0, "Patriots": 3.0, "Cardinals": 3.0, "Vikings": 3.0, "Wendell Smallwood": 3.0, "Ryan Switzer": 2.9, "Ryan Griffin": 2.9, "Roosevelt Nix": 2.9, "Rishard Matthews": 2.8, "Tre'Quan Smith": 2.8, "Jason Croom": 2.7, "James O'Shaughnessy": 2.7, "Gerald Everett": 2.7, "Sam Bradford": 2.6, "Tajae Sharpe": 2.4, "Luke Willson": 2.3, "Marcus Murphy": 2.3, "Rex Burkhead": 2.2, "Andy Janovich": 2.1, "Logan Paulsen": 2.0, "Texans": 2.0, "Latavius Murray": 1.9, "Courtland Sutton": 1.9, "Adam Humphries": 1.8, "Mike Gillislee": 1.8, "Devontae Booker": 1.7, "Stevan Ridley": 1.7, "Logan Thomas": 1.7, "Vernon Davis": 1.7, "Josh Hill": 1.5, "Derek Carrier": 1.5, "Nick Chubb": 1.4, "Zach Line": 1.4, "Lance Kendricks": 1.4, "DJ Chark": 1.3, "Marquez Valdes-Scantling": 1.3, "Damien Williams": 1.2, "Bills": 1.0, "Mike Wallace": 1.0, "Panthers": 1.0, "Steelers": 1.0, "Shaun Wilson": 0.9, "Jermaine Kearse": 0.9, "C.J. Ham": 0.5, "Brandon Wilds": 0.4, "Alex Armah": 0.4, "Jalen Richard": 0.3, "Spencer Ware": 0.3, "Rob Kelley": 0.1, "Derrick Coleman": 0.1, "Vyncint Smith": 0.0, "Dallas Goedert": 0.0, "Tanner McEvoy": 0.0, "Stacy Coley": 0.0, "Trent Taylor": 0.0, "Josh Reynolds": 0.0, "Chad Henne": 0.0, "Anthony Sherman": 0.0, "Justin Davis": 0.0, "Mike Gesicki": 0.0, "Marcedes Lewis": 0.0, "Brandon Zylstra": 0.0, "Kyle Nelson": 0.0, "Colt McCoy": 0.0, "Brock Osweiler": 0.0, "Ricky Ortiz": 0.0, "David Fluellen": 0.0, "Nick Bellore": 0.0, "Orson Charles": 0.0, "Matt LaCosse": 0.0, "Senorise Perry": 0.0, "Jehu Chesson": 0.0, "Shelton Gibson": 0.0, "Charone Peake": 0.0, "Sean Culkin": 0.0, "Derrick Willies": 0.0, "Chad Williams": 0.0, "DaeSean Hamilton": 0.0, "Cody Kessler": 0.0, "Taiwan Jones": 0.0, "MyCole Pruitt": 0.0, "J.J. Jones": 0.0, "Tyler Conklin": 0.0, "Brandon LaFell": 0.0, "Matt Cassel": 0.0, "Derek Watt": 0.0, "Tommy Bohanon": 0.0, "Chris Manhertz": 0.0, "Brandon Weeden": 0.0, "Nathan Peterman": 0.0, "Sean Mannion": 0.0, "Brandon Bolden": 0.0, "Darius Jackson": 0.0, "Raheem Mostert": 0.0, "Jeremy Sprinkle": 0.0, "Anthony Firkser": 0.0, "Austin Carr": 0.0, "Cole Wick": 0.0, "DeShone Kizer": 0.0, "Darrius Heyward-Bey": 0.0, "Durham Smythe": 0.0, "Damion Ratley": 0.0, "Richie James Jr.": 0.0, "Taylor Heinicke": 0.0, "Matthew Slater": 0.0, "Josh McCown": 0.0, "Baker Mayfield": 0.0, "Chad Kelly": 0.0, "James Develin": 0.0, "Justin Hardy": 0.0, "Darius Jennings": 0.0, "Xavier Grimble": 0.0, "Kevin McDermott": 0.0, "J.J. Nelson": 0.0, "Joe Webb III": 0.0, "Brian Hill": 0.0, "Buddy Howell Jr.": 0.0, "Marcus Johnson": 0.0, "De'Anthony Thomas": 0.0, "Neal Sterling": 0.0, "Robert Tonyan": 0.0, "Johnny Mundt": 0.0, "Jaydon Mickens": 0.0, "Trevor Siemian": 0.0, "Brian Hoyer": 0.0, "Trenton Cannon": 0.0, "Brian Quick": 0.0, "Beau Brinkley": 0.0, "Antony Auclair": 0.0, "Teddy Bridgewater": 0.0, "AJ McCarron": 0.0, "Freddie Martino": 0.0, "Jacoby Brissett": 0.0, "C.J. Beathard": 0.0, "Cameron Artis-Payne": 0.0, "Zach Pascal": 0.0, "Alan Cross": 0.0, "Alex Ellis": 0.0, "Geremy Davis": 0.0, "Tommylee Lewis": 0.0, "TJ Jones": 0.0, "Jordan Thomas": 0.0, "Marcus Kemp": 0.0, "Matt Schaub": 0.0, "Joshua Dobbs": 0.0, "Taysom Hill": 0.0, "T.J. Logan": 0.0, "Ryan Hewitt": 0.0, "Cameron Brate": 0.0, "James Winchester": 0.0, "Andre Roberts": 0.0, "Antonio Gates": 0.0, "Gabe Holmes": 0.0, "Dwayne Allen": 0.0, "Lee Smith": 0.0, "Tyler Ervin": 0.0, "Jaylen Samuels": 0.0, "Detrez Newsome": 0.0, "Eric Saubert": 0.0, "Jonnu Smith": 0.0, "DeAndre Carter": 0.0, "Demetrius Harris": 0.0, "Andre Holmes": 0.0, "Levine Toilolo": 0.0, "JoJo Natson Jr.": 0.0, "Marcus Mariota": 0.0, "Josh Rosen": 0.0, "Geno Smith": -0.1, "Jonathan Williams": -0.1, "Chiefs": -3.0}