{
	"Bears": "CHI",
	"Patriots": "NEP",
	"Seahawks": "SEA",
	"Broncos": "DEN",
	"Ravens": "BAL",
	"Colts": "IND",
	"Chargers": "LAC",
	"Bills": "BUF",
	"Bucaneers": "TBB",
	"Texans": "HOU",
	"Falcons": "ATL",
	"Cardinals": "ARI",
	"Steelers": "PIT",
	"Raiders": "OAK",
	"Rams": "LAR",
	"Lions": "DET",
	"Saints": "NOS",
	"Browns": "CLE",
	"Vikings": "MIN",
	"Jaguars": "JAC",
	"Panthers": "CAR",
	"Packers": "GBP",
	"Giants": "NYG",
	"Redskins": "WAS",
	"49ers": "SFO",
	"Cowboys": "DAL",
	"Bengals": "CIN",
	"Chiefs": "KCC",
	"Jets": "NYJ",
	"Titans": "TEN",
	"Dolphins": "MIA",
	"Eagles": "PHI"
}