{"Antonio Brown": 47.5, "Aaron Rodgers": 45.88, "Deshaun Watson": 40.46, "Zach Ertz": 38.0, "Kyle Rudolph": 36.2, "Nick Foles": 35.94, "Christian McCaffrey": 32.8, "Ben Roethlisberger": 32.6, "Robby Anderson": 32.0, "Michael Thomas": 30.9, "Sam Darnold": 29.04, "Robert Woods": 28.4, "Jamaal Williams": 27.6, "Alvin Kamara": 26.5, "C.J. Anderson": 26.2, "Nelson Agholor": 25.6, "Andrew Luck": 25.58, "Baker Mayfield": 24.96, "JuJu Smith-Schuster": 24.5, "Eli Manning": 24.36, "Davante Adams": 24.1, "T.Y. Hilton": 23.8, "Elijah McGuire": 23.5, "DeAndre Hopkins": 22.4, "Kirk Cousins": 22.22, "Mohamed Sanu": 22.0, "Mike Evans": 21.0, "Sony Michel": 20.6, "Matt Ryan": 20.46, "Christopher Herndon IV": 20.2, "Sterling Shepard": 20.0, "Drew Brees": 19.94, "Jameis Winston": 19.84, "Darren Sproles": 19.8, "Julian Edelman": 19.0, "Saquon Barkley": 18.7, "Jacquizz Rodgers": 18.7, "Chester Rogers": 18.4, "Jared Goff": 18.24, "Rashard Higgins": 18.0, "Calvin Ridley": 18.0, "Adam Humphries": 17.9, "Zay Jones": 17.7, "Jeff Driskel": 17.42, "Evan Engram": 17.3, "Jaguars": 17.0, "Dak Prescott": 16.64, "Larry Fitzgerald": 16.58, "Nick Chubb": 16.5, "David Njoku": 16.3, "Leonard Fournette": 16.1, "Ezekiel Elliott": 15.9, "Jake Kumerow": 15.8, "Jaylen Samuels": 15.4, "Taylor Heinicke": 15.26, "Jordan Howard": 15.0, "C.J. Uzomah": 14.9, "Ian Thomas": 14.8, "Dontrelle Inman": 14.6, "Equanimeous St. Brown": 14.4, "Allen Robinson II": 14.4, "George Kittle": 14.4, "Nyheim Hines": 14.3, "Michael Gallup": 14.3, "Falcons": 14.0, "Cowboys": 14.0, "Patriots": 14.0, "Dolphins": 14.0, "Dalvin Cook": 13.8, "David Johnson": 13.7, "Josh Allen": 13.68, "Brian Hill": 13.5, "James White": 13.4, "Adam Thielen": 13.3, "Mitchell Trubisky": 13.14, "Jarius Wright": 12.9, "Julio Jones": 12.8, "Duke Johnson Jr.": 12.6, "Marquez Valdes-Scantling": 12.5, "Dede Westbrook": 12.4, "Ted Ginn Jr.": 12.4, "Trent Sherfield": 12.2, "DeAndre Carter": 12.1, "Jarvis Landry": 11.82, "Anthony Miller": 11.8, "Kenny Golladay": 11.8, "Mark Ingram": 11.3, "Kendrick Bourne": 11.3, "Alshon Jeffery": 11.2, "Curtis Samuel": 11.1, "Ryan Tannehill": 11.04, "Rex Burkhead": 10.9, "Marlon Mack": 10.8, "Darren Fells": 10.8, "D'Onta Foreman": 10.7, "Scott Simonson": 10.6, "Vyncint Smith": 10.5, "TJ Jones": 10.2, "Cole Beasley": 10.0, "Joe Mixon": 9.8, "Breshad Perriman": 9.6, "Jermaine Kearse": 9.5, "Gerald Everett": 9.4, "Kenyan Drake": 9.4, "Brandin Cooks": 9.2, "Robert Foster": 9.2, "Stefon Diggs": 9.0, "Zach Zenner": 8.7, "Nick Mullens": 8.64, "Peyton Barber": 8.6, "Jason Croom": 8.5, "Josh Rosen": 8.38, "Donte Moncrief": 8.3, "Zach Pascal": 8.1, "Rams": 8.0, "49ers": 8.0, "Alfred Blue": 8.0, "Trey Burton": 8.0, "Jets": 8.0, "John Ross": 8.0, "Cordarrelle Patterson": 7.9, "Cody Core": 7.6, "Brandon Bolden": 7.3, "Tom Brady": 7.04, "Bills": 7.0, "Vikings": 7.0, "Bears": 7.0, "Chris Godwin": 6.9, "Kalen Ballage": 6.9, "Danny Amendola": 6.8, "Wendell Smallwood": 6.7, "Demaryius Thomas": 6.7, "Keith Ford": 6.7, "Taylor Gabriel": 6.6, "Jimmy Graham": 6.4, "Josh Reynolds": 6.4, "Saints": 6.0, "Amari Cooper": 6.0, "Dallas Goedert": 6.0, "Andre Roberts": 6.0, "Texans": 6.0, "Vance McDonald": 5.9, "John Kelly": 5.9, "Marquise Goodwin": 5.9, "Eric Ebron": 5.8, "Jeff Wilson Jr.": 5.8, "Austin Hooper": 5.6, "Alex Erickson": 5.5, "Keith Kirkwood": 5.5, "Jordan Akins": 5.3, "Tevin Coleman": 5.1, "Dante Pettis": 5.1, "Eagles": 5.0, "Steelers": 5.0, "Panthers": 5.0, "LeSean McCoy": 4.9, "Ryan Switzer": 4.8, "Taquan Mizzell": 4.8, "Bobo Wilson": 4.8, "Latavius Murray": 4.8, "Matthew Stafford": 4.64, "Lance Kendricks": 4.6, "Theo Riddick": 4.5, "LeGarrette Blount": 4.4, "Devin Funchess": 4.3, "Rashad Greene Sr.": 4.2, "Blake Bortles": 4.06, "Browns": 4.0, "D.J. Moore": 3.9, "Rhett Ellison": 3.8, "DeSean Jackson": 3.8, "Matt Breida": 3.6, "Bennie Fowler": 3.6, "Ryan Griffin": 3.5, "Cody Kessler": 3.44, "Golden Tate": 3.3, "Jordan Matthews": 3.3, "Trent Taylor": 3.3, "DeVante Parker": 3.3, "Matt Cassel": 3.2, "Eli Rogers": 3.2, "Chase Edmonds": 3.1, "Cardinals": 3.0, "Cameron Artis-Payne": 3.0, "Torrey Smith": 2.9, "Tarik Cohen": 2.9, "Ben Braunecker": 2.8, "Blake Jarwin": 2.8, "Cameron Brate": 2.8, "Tyler Higbee": 2.6, "Levine Toilolo": 2.6, "Mike Glennon": 2.52, "Dontrell Hilliard": 2.5, "Jalen Tolliver": 2.5, "Andy Jones": 2.2, "Robert Tonyan": 2.1, "Tre'Quan Smith": 2.1, "Josh Hill": 2.1, "Deonte Thompson": 2.1, "Colts": 2.0, "Bengals": 2.0, "Giovani Bernard": 2.0, "Lions": 2.0, "Giants": 2.0, "Durham Smythe": 1.9, "Jordan Leggett": 1.9, "Brandon Powell": 1.9, "John Phillips": 1.9, "Trenton Cannon": 1.9, "Isaiah McKenzie": 1.8, "Chad Williams": 1.7, "Richard Rodgers": 1.7, "Tommy Bohanon": 1.7, "Noah Brown": 1.6, "Benjamin Watson": 1.6, "Josh Bellamy": 1.6, "Kyle Allen": 1.52, "Elijhaa Penny": 1.5, "Ryan Grant": 1.5, "Kenny Stills": 1.5, "Mike Gesicki": 1.5, "Adam Shaheen": 1.4, "Richie James Jr.": 1.4, "Phillip Dorsett": 1.3, "Kenjon Barner": 1.3, "Ricky Seals-Jones": 1.3, "Danny Vitale": 1.2, "Wayne Gallman": 1.2, "Josh Adams": 1.1, "Seth DeValve": 1.1, "Buccaneers": 1.0, "Corey Coleman": 0.5, "Roosevelt Nix": 0.4, "C.J. Ham": 0.1, "David Morgan": 0.0, "Marvin Hall": 0.0, "JoJo Natson Jr.": 0.0, "Xavier Grimble": 0.0, "Tyrod Taylor": 0.0, "Matt Schaub": 0.0, "Senorise Perry": 0.0, "Kyle Juszczyk": 0.0, "Ben Koyack": 0.0, "Chad Beebe": 0.0, "Victor Bolden Jr.": 0.0, "Russell Gage": 0.0, "Ross Dwelley": 0.0, "Kapri Bibbs": 0.0, "Darius Jackson": 0.0, "Antonio Callaway": 0.0, "Garrett Celek": 0.0, "Trevor Siemian": 0.0, "Buddy Howell Jr.": 0.0, "Lavon Coleman": 0.0, "Allen Hurns": 0.0, "Kevin McDermott": 0.0, "Chris Hogan": 0.0, "Chris Manhertz": 0.0, "Joshua Dobbs": 0.0, "Carlos Hyde": 0.0, "Benny Cunningham": 0.0, "Cody Latimer": 0.0, "Rico Gathers": 0.0, "KhaDarel Hodge": 0.0, "Joe Webb III": 0.0, "C.J. Beathard": 0.0, "Jamize Olawale": 0.0, "Dwayne Washington": 0.0, "Mo Alie-Cox": 0.0, "Damion Ratley": 0.0, "Matthew Slater": 0.0, "Logan Paulsen": 0.0, "Patrick Scales": 0.0, "Brock Osweiler": 0.0, "Boston Scott": 0.0, "Nick Bellore": 0.0, "Ricky Ortiz": 0.0, "Blake Bell": 0.0, "Matt Lengel": 0.0, "Aldrick Robinson": 0.0, "Jerome Cunningham": 0.0, "Logan Thomas": 0.0, "Justin Hardy": 0.0, "Daniel Brown": 0.0, "DeShone Kizer": 0.0, "Teddy Bridgewater": 0.0, "Ameer Abdullah": 0.0, "Alex Armah": 0.0, "Nick O'Leary": 0.0, "Jacob Hollister": 0.0, "Pharoh Cooper": 0.0, "Alex Tanney": 0.0, "Jesse James": 0.0, "Chase Daniel": 0.0, "Patrick DiMarco": 0.0, "Trey Edmunds": 0.0, "Keelan Cole": 0.0, "Dalton Schultz": 0.0, "Brandon Zylstra": 0.0, "Ronald Jones II": 0.0, "Derrick Coleman": 0.0, "Brice Butler": 0.0, "Terrance Williams": 0.0, "Antony Auclair": 0.0, "Dwayne Allen": 0.0, "Matt Barkley": 0.0, "Charone Peake": 0.0, "Jacoby Brissett": 0.0, "Tommylee Lewis": 0.0, "Jordan Wilkins": 0.0, "David Williams": 0.0, "Matt Dayes": 0.0, "Shelton Gibson": 0.0, "Josh Malone": 0.0, "Lance Lenoir": 0.0, "Tyler Conklin": 0.0, "Da'Mari Scott": 0.0, "James Washington": 0.0, "Garrett Dickerson": 0.0, "Clark Harris": 0.0, "Jermaine Gresham": 0.0, "Darrius Heyward-Bey": 0.0, "Josh McCown": 0.0, "T.J. Logan": 0.0, "Eric Saubert": 0.0, "Johnny Mundt": 0.0, "Tom Savage": 0.0, "Mark Walton": 0.0, "James Develin": 0.0, "Michael Burton": 0.0, "Zach Line": 0.0, "Leonte Carroo": 0.0, "Nate Sudfeld": 0.0, "Cooper Rush": 0.0, "De'Angelo Henderson": 0.0, "Jawill Davis": 0.0, "Jordan Thomas": 0.0, "Marcedes Lewis": 0.0, "Deontay Burnett": 0.0, "Auden Tate": 0.0, "Donnie Ernsberger": 0.0, "Rob Gronkowski": 0.0, "Justin Davis": 0.0, "Ryan Hewitt": 0.0, "James O'Shaughnessy": 0.0, "Eric Tomlinson": 0.0, "Luke Willson": 0.0, "Sean Mannion": -0.2, "Brian Hoyer": -0.2, "Stevan Ridley": -0.6, "Rod Smith": -0.7, "J'Mon Moore": -1.0, "Taysom Hill": -1.0, "Packers": -2.0}